{
  "project_info": {
    "project_number": "999007438561",
    "project_id": "ejemplofirebase-29414",
    "storage_bucket": "ejemplofirebase-29414.appspot.com"
  },
  "client": [
    {
      "client_info": {
        "mobilesdk_app_id": "1:999007438561:android:75addf0f8ff721f44a19a0",
        "android_client_info": {
          "package_name": "carlos.robert.ejemplofirebase"
        }
      },
      "oauth_client": [],
      "api_key": [
        {
          "current_key": "AIzaSyDjjCGWvYMchXSCj3UZVc3l8vTmyiJw_TE"
        }
      ],
      "services": {
        "appinvite_service": {
          "other_platform_oauth_client": []
        }
      }
    }
  ],
  "configuration_version": "1"
}